byted_overpass_toutiao_ugc_hot_board_admin/__init__.py
byted_overpass_toutiao_ugc_hot_board_admin-0.0.1.dist-info/METADATA
byted_overpass_toutiao_ugc_hot_board_admin-0.0.1.dist-info/WHEEL
byted_overpass_toutiao_ugc_hot_board_admin-0.0.1.dist-info/top_level.txt
byted_overpass_toutiao_ugc_hot_board_admin-0.0.1.dist-info/RECORD
